README.rst
setup.py
django_fm_minio.egg-info/PKG-INFO
django_fm_minio.egg-info/SOURCES.txt
django_fm_minio.egg-info/dependency_links.txt
django_fm_minio.egg-info/requires.txt
django_fm_minio.egg-info/top_level.txt
fixtures_minio/__init__.py
fixtures_minio/conf.py
fixtures_minio/management/__init__.py
fixtures_minio/management/commands/__init__.py
fixtures_minio/management/commands/fm_list.py
fixtures_minio/management/commands/fm_load.py
fixtures_minio/management/commands/fm_push.py