Metadata-Version: 1.1
Name: django-fm-minio
Version: 0.1.5
Summary: fixtures storage on minio.
Home-page: https://github.com/skob/django-fm-minio
Author: skob
Author-email: skobolo@gmail.com
License: BSD License
Platform: UNKNOWN
Classifier: Environment :: Web Environment
Classifier: Framework :: Django
Classifier: Framework :: Django :: 2.0
Classifier: Intended Audience :: Developers
Classifier: License :: OSI Approved :: BSD License
Classifier: Operating System :: OS Independent
Classifier: Programming Language :: Python
Classifier: Programming Language :: Python :: 3.5
Classifier: Programming Language :: Python :: 3.6
